EventService/__init__.py
EventService/__main__.py
EventService/api.py
EventService/const.py
EventService/service.py
sgb_event-0.1.dist-info/METADATA
sgb_event-0.1.dist-info/WHEEL
sgb_event-0.1.dist-info/entry_points.txt
sgb_event-0.1.dist-info/top_level.txt
sgb_event-0.1.dist-info/RECORD
