Metadata-Version: 2.2
Name: sgb-event
Version: 0.1
Summary: SGB Log and Event service package
Home-page: https://none.com/
Author: Nikita Karachentsev
Author-email: n.karachencev@sf-m.biz
License: MIT
Requires-Dist: isgb
Requires-Dist: telegram-send
Dynamic: author
Dynamic: author-email
Dynamic: description-content-type
Dynamic: home-page
Dynamic: license
Dynamic: requires-dist
Dynamic: summary
